smpl_ml/__init__.py
smpl_ml/classification_helpers.py
smpl_ml/smpl_ml.py
SmplML-1.0.6.dist-info/LICENSE
SmplML-1.0.6.dist-info/METADATA
SmplML-1.0.6.dist-info/WHEEL
SmplML-1.0.6.dist-info/top_level.txt
SmplML-1.0.6.dist-info/RECORD
