Metadata-Version: 2.1
Name: SmplML
Version: 1.0.6
Summary: SmplML is a user-friendly Python module for streamlined machine learning classification and regression. It offers intuitive functionality for data preprocessing, model training, and evaluation. Ideal for beginners and experts alike, SmplML simplifies ML tasks, enabling you to gain valuable insights from your data with ease.
Home-page: https://github.com/JhunBrian/SmplML
Author: Jhun Brian Andam
Author-email: andam.jhunbrian@gmail.com
License: MIT
Keywords: Machine Learning,Classification,Regression
Classifier: Development Status :: 5 - Production/Stable
Classifier: Intended Audience :: Science/Research
Classifier: Operating System :: Microsoft :: Windows :: Windows 10
Classifier: License :: OSI Approved :: MIT License
Classifier: Programming Language :: Python :: 3
License-File: LICENSE
Requires-Dist: pandas
Requires-Dist: numpy
Requires-Dist: scikit-learn
